iita_python/__init__.py
iita_python/_version.py
iita_python/additional_ce.py
iita_python/dataset.py
iita_python/fit_metrics.py
iita_python/quasiorder.py
iita_python/utils.py
iita_python-1.3.dist-info/METADATA
iita_python-1.3.dist-info/WHEEL
iita_python-1.3.dist-info/top_level.txt
iita_python-1.3.dist-info/RECORD
