Metadata-Version: 2.4
Name: iita_python
Version: 1.3
Summary: IITA algorithm in python
Author-email: Aliaksei Badnarchuk <alexejbodnarchuk@gmail.com>
Requires-Python: >=3.9
Requires-Dist: numpy
Requires-Dist: pandas
